hybrid_pke-1.0.2.dist-info/METADATA
hybrid_pke-1.0.2.dist-info/WHEEL
hybrid_pke-1.0.2.dist-info/license_files/LICENSE
hybrid_pke-1.0.2.dist-info/license_files/NOTICE
hybrid_pke/__init__.py
hybrid_pke/hybrid_pke.cpython-310-x86_64-linux-gnu.so
hybrid_pke-1.0.2.dist-info/RECORD
