Metadata-Version: 2.1
Name: hybrid_pke
Version: 1.0.2
Classifier: License :: OSI Approved :: Apache Software License
Classifier: Programming Language :: Rust
Classifier: Programming Language :: Python
Classifier: Programming Language :: Python :: Implementation :: CPython
Classifier: Topic :: Security :: Cryptography
License-File: LICENSE
License-File: NOTICE
Summary: The Hybrid Public Key Encryption (HPKE) standard in Python
Requires-Python: >=3.8
Project-URL: repository, https://github.com/capeprivacy/hybrid-pke
